blacked/__init__.py
blacked/__main__.py
blacked/blacked20_8b1.py
blacked/config_parser.py
blacked-0.1.0a4.dist-info/entry_points.txt
blacked-0.1.0a4.dist-info/WHEEL
blacked-0.1.0a4.dist-info/METADATA
blacked-0.1.0a4.dist-info/RECORD
