Metadata-Version: 2.1
Name: blacked
Version: 0.1.0a4
Summary: 
Home-page: https://github.com/MrMrRobat/blacked
Author: MrMrRobat
Author-email: appkiller16@gmail.com
Requires-Python: >=3.6,<4.0
Classifier: Programming Language :: Python :: 3
Classifier: Programming Language :: Python :: 3.6
Classifier: Programming Language :: Python :: 3.7
Classifier: Programming Language :: Python :: 3.8
Classifier: Programming Language :: Python :: 3.9
Requires-Dist: black (>=18.4a0)
Project-URL: Repository, https://github.com/MrMrRobat/blacked
